.class public TestB
.super java/lang/Object


;
;standard initializer (calls java.lang.Object's initializer)
;
.method public <init>()V
aload_0
invokespecial java/lang/Object/<init>()V
return
.end method


;
;main() - main method follows
;
.method public static main([Ljava/lang/String;)V
   .limit locals 8
   .limit stack 207
   iconst_2
   newarray int
   astore 1
   iconst_2
   newarray long
   astore 2
   new 'Sum'
   dup
   invokespecial 'Sum/<init>()V'
   astore 7
   aload 1
   iconst_0
   iconst_3
   iastore
   aload 2
   iconst_0
   iconst_3
   i2l
   lastore
   aload 1
   iconst_1
   ldc 7
   iastore
   aload 2
   iconst_1
   ldc 7
   i2l
   lastore
   aload 1
   iconst_0
   iaload
   istore 3
   iload 3
   aload 1
   iconst_1
   iaload
   iadd
   istore 4
   aload 2
   iconst_0
   laload
   lstore 5
   iload 3
   i2l
   lload 5
   lcmp
   ifeq TRUE_LABEL_0
   iconst_0
   goto NEXT_LABEL_1
TRUE_LABEL_0:
   iconst_1
NEXT_LABEL_1:
   ifeq IF_FALSE_3
IF_TRUE_2:
   getstatic java/lang/System/out Ljava/io/PrintStream;
   iconst_1
   invokestatic java/lang/Integer/toString(I)Ljava/lang/String;
   invokevirtual java/io/PrintStream/println(Ljava/lang/String;)V
IF_FALSE_3:


   return
.end method
